toputils/__VERSION__.py
toputils/__init__.py
toputils/db/__init__.py
toputils/db/db.py
toputils/example_cnfs/db.cnf
toputils/example_cnfs/rmq.cnf
toputils/rmq/__init__.py
toputils/rmq/utils.py
toputils/rounder/__init__.py
toputils/rounder/roll_scale.py
toputils/rounder/rounder.py
toputils/tests/__init__.py
toputils/tests/db_test.py
toputils/tests/rmq_test.py
toputils/tests/rounder_test.py
toputils-3.0.1.dist-info/METADATA
toputils-3.0.1.dist-info/RECORD
toputils-3.0.1.dist-info/WHEEL
toputils-3.0.1.dist-info/top_level.txt
