Metadata-Version: 2.1
Name: toputils
Version: 3.0.1
Summary: Collection of scripting utilities
Home-page: https://github.com/5uper5hoot/toputils
Author: Peter Schutt
Author-email: peter@topsport.com.au
License: MIT
Requires-Dist: backoff (>=1.4.3)
Requires-Dist: pika (>=0.11.0)
Requires-Dist: sortedcontainers (>=1.5.9)
Provides-Extra: dev
Requires-Dist: pytest; extra == 'dev'
